setup.py
paralleltools/__init__.py
paralleltools/supervisors.py
paralleltools/workers.py
paralleltools.egg-info/PKG-INFO
paralleltools.egg-info/SOURCES.txt
paralleltools.egg-info/dependency_links.txt
paralleltools.egg-info/top_level.txt