Metadata-Version: 1.0
Name: paralleltools
Version: 0.0.2
Summary: A collection of basic list functions which can be run in parallel mode (both sync or async).
Home-page: http://github.com/andrusha/paralleltools
Author: Andrew Korzhuev
Author-email: korzhuev@andrusha.me
License: MIT
Keywords: parallel threading map filter reduce async
Platform: UNKNOWN
Classifier: Development Status :: 4 - Beta
Classifier: Intended Audience :: Developers
Classifier: License :: OSI Approved :: MIT License
Classifier: Programming Language :: Python
Classifier: Programming Language :: Python :: 2.6
Classifier: Programming Language :: Python :: 2.7
Classifier: Programming Language :: Python :: 3
Classifier: Programming Language :: Python :: 3.2
Classifier: Operating System :: OS Independent
Classifier: Topic :: Software Development
Classifier: Topic :: Software Development :: Libraries
Classifier: Topic :: Software Development :: Libraries :: Python Modules
